vllm_ascend/__init__.py
vllm_ascend/_version.py
vllm_ascend/envs.py
vllm_ascend/libvllm_ascend_kernels.so
vllm_ascend/platform.py
vllm_ascend/utils.py
vllm_ascend/vllm_ascend_C.cpython-311-x86_64-linux-gnu.so
vllm_ascend/attention/__init__.py
vllm_ascend/attention/attention.py
vllm_ascend/attention/attention_v1.py
vllm_ascend/attention/mla_v1.py
vllm_ascend/core/__init__.py
vllm_ascend/core/schedule_config.py
vllm_ascend/core/scheduler.py
vllm_ascend/device_allocator/__init__.py
vllm_ascend/device_allocator/camem.py
vllm_ascend/distributed/__init__.py
vllm_ascend/distributed/communicator.py
vllm_ascend/distributed/llmdatadist_connector.py
vllm_ascend/distributed/parallel_state.py
vllm_ascend/distributed/device_communicators/__init__.py
vllm_ascend/distributed/device_communicators/pyhccl.py
vllm_ascend/distributed/device_communicators/pyhccl_wrapper.py
vllm_ascend/distributed/kv_transfer/__init__.py
vllm_ascend/distributed/kv_transfer/simple_buffer.py
vllm_ascend/distributed/kv_transfer/simple_connector.py
vllm_ascend/distributed/kv_transfer/simple_pipe.py
vllm_ascend/distributed/kv_transfer/utils.py
vllm_ascend/lora/__init__.py
vllm_ascend/lora/punica_wrapper/__init__.py
vllm_ascend/lora/punica_wrapper/punica_npu.py
vllm_ascend/models/__init__.py
vllm_ascend/models/deepseek_mtp.py
vllm_ascend/models/deepseek_v2.py
vllm_ascend/models/qwen2_5_vl.py
vllm_ascend/models/qwen2_vl.py
vllm_ascend/ops/__init__.py
vllm_ascend/ops/activation.py
vllm_ascend/ops/attention.py
vllm_ascend/ops/cache.py
vllm_ascend/ops/common_fused_moe.py
vllm_ascend/ops/fused_moe.py
vllm_ascend/ops/layernorm.py
vllm_ascend/ops/rotary_embedding.py
vllm_ascend/ops/vocab_parallel_embedding.py
vllm_ascend/patch/__init__.py
vllm_ascend/patch/platform/__init__.py
vllm_ascend/patch/platform/patch_0_8_5/__init__.py
vllm_ascend/patch/platform/patch_common/__init__.py
vllm_ascend/patch/platform/patch_common/patch_distributed.py
vllm_ascend/patch/platform/patch_main/__init__.py
lishuqiaovs-0.8.5rc15.dist-info/LICENSE
lishuqiaovs-0.8.5rc15.dist-info/METADATA
lishuqiaovs-0.8.5rc15.dist-info/WHEEL
lishuqiaovs-0.8.5rc15.dist-info/entry_points.txt
lishuqiaovs-0.8.5rc15.dist-info/top_level.txt
lishuqiaovs-0.8.5rc15.dist-info/RECORD
